deltalake2db/__init__.py
deltalake2db/azure_helper.py
deltalake2db/delta_meta_retrieval.py
deltalake2db/duckdb.py
deltalake2db/filter_by_meta.py
deltalake2db/fsspec_fs.py
deltalake2db/polars.py
deltalake2db/protocol_check.py
deltalake2db/sql_utils.py
deltalake2db-1.2.2.dist-info/METADATA
deltalake2db-1.2.2.dist-info/WHEEL
deltalake2db-1.2.2.dist-info/RECORD
