Metadata-Version: 2.4
Name: deltalake2db
Version: 1.2.2
Author-email: Adrian Ehrsam <adrian.ehrsam@bmsuisse.ch>
Requires-Python: ~=3.9
Requires-Dist: polars>=1.12
Requires-Dist: sqlglot>=22.2.1
Provides-Extra: azure
Requires-Dist: azure-identity<2,>=1.16.0; extra == 'azure'
